<?xml version="1.0"?>
<opencv_storage>
<stage3>
  <maxWeakCount>55</maxWeakCount>
  <stageThreshold>-1.5087250471115112e+00</stageThreshold>
  <weakClassifiers>
    <_>
      <internalNodes>
        0 -1 2913 -134742017 -201400321 -54601859 -84215044 -139600897
        -85017611 -121579272 -357903120</internalNodes>
      <leafValues>
        -4.2600139975547791e-01 2.0212604105472565e-01</leafValues></_>
    <_>
      <internalNodes>
        0 -1 5713 -2147482608 -554214787 -591201297 -176688331
        -321874280 -16807186 -869859349 -546570289</internalNodes>
      <leafValues>
        -3.2387554645538330e-01 2.7303367853164673e-01</leafValues></_>
    <_>
      <internalNodes>
        0 -1 8371 -1431663043 77250539 -1464222211 -1179291785
        -1678115413 -1485195283 -21066066 -1140904709</internalNodes>
      <leafValues>
        -2.1028491854667664e-01 3.1520870327949524e-01</leafValues></_>
    <_>
      <internalNodes>
        0 -1 430 -134227969 -168558697 2147171126 -147845358 -689973361
        -139757645 -113774854 -15467973</internalNodes>
      <leafValues>
        -1.5134568512439728e-01 4.2621684074401855e-01</leafValues></_>
    <_>
      <internalNodes>
        0 -1 5599 -171647016 -802662184 -762394520 1095455864
        -1113534328 172900352 -961498934 53211599</internalNodes>
      <leafValues>
        -2.6428431272506714e-01 2.3799651861190796e-01</leafValues></_>
    <_>
      <internalNodes>
        0 -1 5388 -574620225 -1151608897 -1157081360 -644155310
        -855996744 -1171136079 8552464 682734271</internalNodes>
      <leafValues>
        -2.3621501028537750e-01 2.3880253732204437e-01</leafValues></_>
    <_>
      <internalNodes>
        0 -1 4894 -2069752575 -1436108936 -1522467596 -727707648
        -1935866300 -348094423 -325260544 -2064627340</internalNodes>
      <leafValues>
        -4.4744554162025452e-01 1.2140763550996780e-01</leafValues></_>
    <_>
      <internalNodes>
        0 -1 1135 -192951518 -286913968 -1806048528 -267232448
        -2062692588 -1526070855 -52513296 -234695552</internalNodes>
      <leafValues>
        -3.0100631713867188e-01 1.7891529202461243e-01</leafValues></_>
    <_>
      <internalNodes>
        0 -1 4173 2020670140 -53980112 1525039168 1361200650 -132443960
        -1962353024 -261975222 285430879</internalNodes>
      <leafValues>
        -2.5340074300765991e-01 2.1942944824695587e-01</leafValues></_>
    <_>
      <internalNodes>
        0 -1 787 -925767646 -2074551937 -938676619 -2061502681
        -924520461 -823041657 -993764865 -573178541</internalNodes>
      <leafValues>
        -2.4855235219001770e-01 2.1608439087867737e-01</leafValues></_>
    <_>
      <internalNodes>
        0 -1 6068 -1332801743 2010403596 -1953201601 1072368890
        -1170142800 942365093 -1417672516 -1146471568</internalNodes>
      <leafValues>
        -2.3813109099864960e-01 2.2507072985172272e-01</leafValues></_>
    <_>
      <internalNodes>
        0 -1 6913 -2098772893 -1092722562 -2062559235 -86877827
        -660648876 -1141176305 -129832212 -533533212</internalNodes>
      <leafValues>
        -2.6780667901039124e-01 1.9814302027225494e-01</leafValues></_>
    <_>
      <internalNodes>
        0 -1 8123 -996684278 -1258843563 -627334496 -219555984
        -255798970 2020161561 1479975364 -799802438</internalNodes>
      <leafValues>
        -3.2008022069931030e-01 1.7101433873176575e-01</leafValues></_>
    <_>
      <internalNodes>
        0 -1 6655 -17147140 1509777144 -20251025 -2126295892 -840769912
        -155691955 -1174220582 84661967</internalNodes>
      <leafValues>
        -2.0122280716896057e-01 2.5381988286972046e-01</leafValues></_>
    <_>
      <internalNodes>
        0 -1 3773 -1909310416 -1661046380 -1545924139 -1376836227
        -1148147537 -880050006 -17936971 -1948288747</internalNodes>
      <leafValues>
        -3.0683410167694092e-01 1.6130521893501282e-01</leafValues></_>
    <_>
      <internalNodes>
        0 -1 8086 -520425745 -793787916 -1592088428 -1604661850
        -144517052 2037323863 -185800060 -1264256340</internalNodes>
      <leafValues>
        -2.4862442910671234e-01 2.0549996197223663e-01</leafValues></_>
    <_>
      <internalNodes>
        0 -1 427 -50474029 -636493590 -142020534 1460701458 -143131473
        -579813484 1086550971 -78416645</internalNodes>
      <leafValues>
        -1.6752637922763824e-01 3.1225636601448059e-01</leafValues></_>
    <_>
      <internalNodes>
        0 -1 7270 -1567751118 660765597 -362877964 -1295861608
        -1650429120 242691084 -526683692 -1607451420</internalNodes>
      <leafValues>
        -3.9560553431510925e-01 1.3491633534431458e-01</leafValues></_>
    <_>
      <internalNodes>
        0 -1 54 1349550990 -797911987 -1333777728 1120032253 2058439928
        1790614204 1097872000 1655932375</internalNodes>
      <leafValues>
        -3.2804855704307556e-01 1.4657372236251831e-01</leafValues></_>
    <_>
      <internalNodes>
        0 -1 6808 -1460796395 -264615393 -104564247 -320964677 -70311971
        -1081571189 2062208733 -288311939</internalNodes>
      <leafValues>
        -2.2463664412498474e-01 2.1688149869441986e-01</leafValues></_>
    <_>
      <internalNodes>
        0 -1 3183 -79718437 1400398833 -221040598 1567107987 -461905960
        1044514176 -128307526 -662571829</internalNodes>
      <leafValues>
        -1.6915138065814972e-01 3.1107443571090698e-01</leafValues></_>
    <_>
      <internalNodes>
        0 -1 2210 1855401205 -1065858147 -832959520 1314940148
        -604113040 -420829848 -337266672 -1743192780</internalNodes>
      <leafValues>
        -3.6242520809173584e-01 1.5057897567749023e-01</leafValues></_>
    <_>
      <internalNodes>
        0 -1 8000 -1529950919 37769624 -1626897890 -1594980880 741499112
        63592449 701107356 -1392552711</internalNodes>
      <leafValues>
        -2.8467264771461487e-01 1.7676055431365967e-01</leafValues></_>
    <_>
      <internalNodes>
        0 -1 4223 -167870118 1559098965 -193038282 -1177833252
        -256379710 -180075938 -1404907445 1130101838</internalNodes>
      <leafValues>
        -2.0150525867938995e-01 2.4546782672405243e-01</leafValues></_>
    <_>
      <internalNodes>
        0 -1 2017 -1638203276 631200203 -1803489889 146739119
        -1149276124 -757612377 -1733753796 -1090902246</internalNodes>
      <leafValues>
        -2.6172718405723572e-01 1.8057216703891754e-01</leafValues></_>
    <_>
      <internalNodes>
        0 -1 8350 -502112733 -1036693499 -623491390 -1157966200
        278889028 1229139066 1102672006 -257188662</internalNodes>
      <leafValues>
        -2.4530659615993500e-01 1.9309985637664795e-01</leafValues></_>
    <_>
      <internalNodes>
        0 -1 8401 -1430692835 -1163112421 -1962926860 -1060612218
        684165635 1348192514 64742592 -1493547164</internalNodes>
      <leafValues>
        -2.7432718873023987e-01 1.7449527978897095e-01</leafValues></_>
    <_>
      <internalNodes>
        0 -1 6057 -493188582 916111768 268961356 289511936 -1416906064
        158381192 230442988 199819288</internalNodes>
      <leafValues>
        -2.6785221695899963e-01 1.8425719439983368e-01</leafValues></_>
    <_>
      <internalNodes>
        0 -1 3220 -1368386767 -1078075486 -554715683 -2080440449
        -8634421 -939557379 2004742111 -3480323</internalNodes>
      <leafValues>
        -1.9140999019145966e-01 2.6208230853080750e-01</leafValues></_>
    <_>
      <internalNodes>
        0 -1 2492 -511705601 -655366090 -788989842 -750600709 -148949806
        -1708473382 1967945082 -628884017</internalNodes>
      <leafValues>
        -1.3472513854503632e-01 3.6867588758468628e-01</leafValues></_>
    <_>
      <internalNodes>
        0 -1 5277 -65014004 825672127 -1608969863 2065039063 474103872
        754000043 193502860 -1133323654</internalNodes>
      <leafValues>
        -2.4489471316337585e-01 2.0301920175552368e-01</leafValues></_>
    <_>
      <internalNodes>
        0 -1 1744 -2096935930 -290662128 -716091824 -188559356 269199537
        -1916140894 -796855324 -1329829440</internalNodes>
      <leafValues>
        -3.1889995932579041e-01 1.5328739583492279e-01</leafValues></_>
    <_>
      <internalNodes>
        0 -1 5808 -1596051374 -1461436419 -1835900990 -1065337512
        -1762600320 -626474632 -2113819294 17915151</internalNodes>
      <leafValues>
        -3.1741040945053101e-01 1.6098272800445557e-01</leafValues></_>
    <_>
      <internalNodes>
        0 -1 2950 -1383385579 -1434434000 -666920702 -495692560
        147669005 -2037776325 4908963 -1577972176</internalNodes>
      <leafValues>
        -3.2279822230339050e-01 1.4257036149501801e-01</leafValues></_>
    <_>
      <internalNodes>
        0 -1 6342 -50341892 -1094994844 -873727444 836706380 -633700158
        -756588598 -285182369 1364191327</internalNodes>
      <leafValues>
        -1.6839331388473511e-01 2.7394986152648926e-01</leafValues></_>
    <_>
      <internalNodes>
        0 -1 2501 1193233775 1920498294 -1004766205 1757457310
        -137139636 2032698865 -381319924 -1439411119</internalNodes>
      <leafValues>
        -2.7695298194885254e-01 1.6895131766796112e-01</leafValues></_>
    <_>
      <internalNodes>
        0 -1 8463 569558111 -1363309057 -134897744 -1838962691
        2088736149 -1497563164 -1929527826 -1142993154</internalNodes>
      <leafValues>
        -1.8762604892253876e-01 2.4457724392414093e-01</leafValues></_>
    <_>
      <internalNodes>
        0 -1 6500 -1095411619 -117688903 -605987425 -1510313660
        -78734720 -1182097341 -1171751435 -307080379</internalNodes>
      <leafValues>
        -2.2299949824810028e-01 2.1182043850421906e-01</leafValues></_>
    <_>
      <internalNodes>
        0 -1 82 138510628 -1825035732 2046833654 -719141272 -503253961
        -110601508 -118988321 1156961235</internalNodes>
      <leafValues>
        -2.4919010698795319e-01 1.9305849075317383e-01</leafValues></_>
    <_>
      <internalNodes>
        0 -1 6000 -1293070845 753958174 -700390790 -218857324 848057348
        -1474856929 710605012 -1569675596</internalNodes>
      <leafValues>
        -3.5052254796028137e-01 1.3521085679531097e-01</leafValues></_>
    <_>
      <internalNodes>
        0 -1 7473 1441527318 -1152115108 -201818178 1508707567
        -174946152 -25166315 -518483058 -1476141126</internalNodes>
      <leafValues>
        -1.7410525679588318e-01 2.7183887362480164e-01</leafValues></_>
    <_>
      <internalNodes>
        0 -1 3807 1247325776 2059391742 473021805 -814944110 -337323620
        -626813150 -1509904436 -618725526</internalNodes>
      <leafValues>
        -2.2600568830966949e-01 2.0464211702346802e-01</leafValues></_>
    <_>
      <internalNodes>
        0 -1 5892 785650184 -1375038767 -66001644 -86082512 -1869992652
        183060507 -341150880 -1540297708</internalNodes>
      <leafValues>
        -4.4330251216888428e-01 1.0631734132766724e-01</leafValues></_>
    <_>
      <internalNodes>
        0 -1 3645 -9057462 1903596660 1655762956 -540736962 1818816234
        -974461229 -1034756405 -247735205</internalNodes>
      <leafValues>
        -1.5699534118175507e-01 3.1651061773300171e-01</leafValues></_>
    <_>
      <internalNodes>
        0 -1 720 -617605595 1345672280 422028795 846599838 -1111479520
        2075852825 -589024636 -1092076264</internalNodes>
      <leafValues>
        -2.8157559037208557e-01 1.7694422602653503e-01</leafValues></_>
    <_>
      <internalNodes>
        0 -1 7816 -1428346107 -2077875646 353029400 1950536720
        -2009034694 -1540602855 403180798 -1985263571</internalNodes>
      <leafValues>
        -2.6222434639930725e-01 1.8359608948230743e-01</leafValues></_>
    <_>
      <internalNodes>
        0 -1 4519 1789390749 -790170500 1573241565 -816909164
        -1505805168 -92512584 -64913461 123598710</internalNodes>
      <leafValues>
        -2.0531301200389862e-01 2.4748840928077698e-01</leafValues></_>
    <_>
      <internalNodes>
        0 -1 5284 -1533520615 1015566640 -466101935 -53709500
        -1471644197 -121044987 -829932567 -844310139</internalNodes>
      <leafValues>
        -2.5459146499633789e-01 1.9380371272563934e-01</leafValues></_>
    <_>
      <internalNodes>
        0 -1 4120 1929134970 -872037664 2030586562 159961256 -155690558
        -926416552 411941138 1179856773</internalNodes>
      <leafValues>
        -2.9282426834106445e-01 1.6507683694362640e-01</leafValues></_>
    <_>
      <internalNodes>
        0 -1 5017 -276906879 1394399067 -651461659 -56427474 1827235576
        -1473209389 2093273956 -16337154</internalNodes>
      <leafValues>
        -2.1918597817420959e-01 2.1844109892845154e-01</leafValues></_>
    <_>
      <internalNodes>
        0 -1 6379 -1027425476 714205328 1711982695 1103151758 748347988
        1287165138 -968548120 82169587</internalNodes>
      <leafValues>
        -3.1069812178611755e-01 1.5257298946380615e-01</leafValues></_>
    <_>
      <internalNodes>
        0 -1 0 784016820 -1906790195 1568674126 -789032730 -83568978
        847903929 -384960289 -1195839505</internalNodes>
      <leafValues>
        -2.1624666452407837e-01 2.2187420725822449e-01</leafValues></_>
    <_>
      <internalNodes>
        0 -1 5026 -1243090956 -743688050 1589526516 1573622954
        1348239834 -1374673194 -1206714629 -513810529</internalNodes>
      <leafValues>
        -1.4220276474952698e-01 3.3496317267417908e-01</leafValues></_>
    <_>
      <internalNodes>
        0 -1 349 -759443889 1513419776 -1656826042 88146496 996862719
        1116047812 1646080864 1356327681</internalNodes>
      <leafValues>
        -2.6234164834022522e-01 1.8620657920837402e-01</leafValues></_>
    <_>
      <internalNodes>
        0 -1 2685 -996024560 -870306265 -84918341 -1015153409 1648875234
        1543339974 -334053779 -920845059</internalNodes>
      <leafValues>
        -2.0568765699863434e-01 2.3093737661838531e-01</leafValues></_></weakClassifiers></stage3>
</opencv_storage>
