<?xml version="1.0"?>
<opencv_storage>
<stage7>
  <maxWeakCount>27</maxWeakCount>
  <stageThreshold>-1.6346044540405273e+00</stageThreshold>
  <weakClassifiers>
    <_>
      <internalNodes>
        0 -1 3688 -12327294 -211836528 893583516 -638606604 1372914347
        989952256 2010450699 -145754165</internalNodes>
      <leafValues>
        -7.6883184909820557e-01 -4.0918803215026855e-01</leafValues></_>
    <_>
      <internalNodes>
        0 -1 39945 1412862168 2046773688 829061526 -1784824885
        1344886975 514555317 -57909974 1810585411</internalNodes>
      <leafValues>
        -4.3548738956451416e-01 9.0702883899211884e-02</leafValues></_>
    <_>
      <internalNodes>
        0 -1 72481 -98297856 1502444518 671491625 996171334 441860297
        1926627873 -251560274 1210065738</internalNodes>
      <leafValues>
        -4.0015864372253418e-01 1.7727151513099670e-01</leafValues></_>
    <_>
      <internalNodes>
        0 -1 76554 1987930672 -1629539367 1619899419 -1341196525
        1795511156 -901963476 -223479388 -256726692</internalNodes>
      <leafValues>
        -4.1012349724769592e-01 1.6989305615425110e-01</leafValues></_>
    <_>
      <internalNodes>
        0 -1 4913 -683048960 864519191 813917248 -1586063968 672811073
        324743216 520048692 1346570067</internalNodes>
      <leafValues>
        -4.5318064093589783e-01 1.8699285387992859e-01</leafValues></_>
    <_>
      <internalNodes>
        0 -1 46994 -38211490 -878963686 1799682567 796105522 -19736886
        -376944127 1316197034 948953077</internalNodes>
      <leafValues>
        -2.7526253461837769e-01 2.5863599777221680e-01</leafValues></_>
    <_>
      <internalNodes>
        0 -1 71609 1174846147 1325388143 -1373897487 -661598094
        -894719524 -29387975 213548671 -618955909</internalNodes>
      <leafValues>
        -2.9344254732131958e-01 2.4975526332855225e-01</leafValues></_>
    <_>
      <internalNodes>
        0 -1 9025 -560547258 -204427650 -84484379 -1848606945 1570705801
        1298618365 -185478946 -551844593</internalNodes>
      <leafValues>
        -2.3784413933753967e-01 2.9974398016929626e-01</leafValues></_>
    <_>
      <internalNodes>
        0 -1 62374 -18221440 515092544 -197622496 1314198094 -1099114750
        815666099 215613255 -730562750</internalNodes>
      <leafValues>
        -5.3383678197860718e-01 1.4245188236236572e-01</leafValues></_>
    <_>
      <internalNodes>
        0 -1 15373 1589955304 -120447497 -556761231 -68093317 -61079674
        -1863602007 1053519368 29943434</internalNodes>
      <leafValues>
        -4.3917751312255859e-01 1.7673863470554352e-01</leafValues></_>
    <_>
      <internalNodes>
        0 -1 78794 -772035188 -388962481 -2078616236 -272645509
        -1148471928 -1202478789 -881425854 -1642621880</internalNodes>
      <leafValues>
        -3.3212718367576599e-01 2.1874834597110748e-01</leafValues></_>
    <_>
      <internalNodes>
        0 -1 76878 -51171541 -773859565 -803165762 1783002076 -13957818
        -49073077 -1824390829 -251766172</internalNodes>
      <leafValues>
        -4.1262456774711609e-01 1.8063265085220337e-01</leafValues></_>
    <_>
      <internalNodes>
        0 -1 3298 -330716800 -395666032 -1858070912 -1994619463
        229574557 1059586410 327160027 -448309550</internalNodes>
      <leafValues>
        -2.9285788536071777e-01 2.5256803631782532e-01</leafValues></_>
    <_>
      <internalNodes>
        0 -1 68430 -427586513 1284497789 -599206668 -493718626
        -909380943 1535807497 763615697 -253965324</internalNodes>
      <leafValues>
        -3.6180871725082397e-01 1.9883270561695099e-01</leafValues></_>
    <_>
      <internalNodes>
        0 -1 914 1641281460 185064392 -581707789 398616144 944866021
        -1379393308 885288961 -807964269</internalNodes>
      <leafValues>
        -3.1795951724052429e-01 2.3345813155174255e-01</leafValues></_>
    <_>
      <internalNodes>
        0 -1 65565 675285016 533352792 810915266 1968854404 101229806
        204308908 1103247902 4340944</internalNodes>
      <leafValues>
        -3.8892069458961487e-01 1.8482154607772827e-01</leafValues></_>
    <_>
      <internalNodes>
        0 -1 107299 -213719346 55827375 -318421010 1124165150 -793924208
        1614816763 1705485128 373457248</internalNodes>
      <leafValues>
        -3.6413785815238953e-01 2.0487119257450104e-01</leafValues></_>
    <_>
      <internalNodes>
        0 -1 7923 -34551741 -89444683 -1158185355 -472188129 877762234
        -1504119852 1010095757 2068834143</internalNodes>
      <leafValues>
        -2.6374381780624390e-01 2.9194062948226929e-01</leafValues></_>
    <_>
      <internalNodes>
        0 -1 98395 2117740047 412857212 -1937067751 782160767 1001073217
        1791623168 -83075210 -282789180</internalNodes>
      <leafValues>
        -4.9924716353416443e-01 1.5673448145389557e-01</leafValues></_>
    <_>
      <internalNodes>
        0 -1 117299 -195894450 -129105448 1409405126 -890965748
        -368519163 -2129948652 -517820412 1952276854</internalNodes>
      <leafValues>
        -6.0370725393295288e-01 1.1486963182687759e-01</leafValues></_>
    <_>
      <internalNodes>
        0 -1 75357 -211864209 -1579949509 1073992572 1519786847
        1776758335 462095432 2041104724 -221184540</internalNodes>
      <leafValues>
        -4.1377109289169312e-01 1.7396995425224304e-01</leafValues></_>
    <_>
      <internalNodes>
        0 -1 26378 -1210601491 1469081285 -1525238458 1193426687
        -1906336555 -1743722341 -553393445 1654605911</internalNodes>
      <leafValues>
        -2.8039920330047607e-01 2.6698848605155945e-01</leafValues></_>
    <_>
      <internalNodes>
        0 -1 13677 -421678298 -86163190 -1073599340 -803225469
        1540434409 -1959722829 814301316 921826071</internalNodes>
      <leafValues>
        -3.4614998102188110e-01 2.1235710382461548e-01</leafValues></_>
    <_>
      <internalNodes>
        0 -1 24886 -896347501 -235868552 -1342321677 -36835337
        -1757843535 -1200717828 510950319 -1653770857</internalNodes>
      <leafValues>
        -1.9018787145614624e-01 3.9570328593254089e-01</leafValues></_>
    <_>
      <internalNodes>
        0 -1 55445 -1173936842 -1089244587 -805203696 1591218439
        -1551426775 -228915073 -1315922284 -1598944352</internalNodes>
      <leafValues>
        -4.2489844560623169e-01 1.8579716980457306e-01</leafValues></_>
    <_>
      <internalNodes>
        0 -1 92597 -704132465 -1659044351 -50368553 -149718433 -25501732
        -1259675650 1592921247 1931723706</internalNodes>
      <leafValues>
        -1.8796715140342712e-01 4.1198012232780457e-01</leafValues></_>
    <_>
      <internalNodes>
        0 -1 2038 -1893888352 141067234 -1022815888 -1484142714
        149615573 -1934618320 1883441170 1143467363</internalNodes>
      <leafValues>
        -4.0273317694664001e-01 1.9867043197154999e-01</leafValues></_></weakClassifiers></stage7>
</opencv_storage>
