<?xml version="1.0"?>
<opencv_storage>
<stage8>
  <maxWeakCount>59</maxWeakCount>
  <stageThreshold>-1.4045031070709229e+00</stageThreshold>
  <weakClassifiers>
    <_>
      <internalNodes>
        0 -1 8368 -272897317 -2505329 -502661044 -79310689 -744494706
        -1152827385 -1718957058 -15466497</internalNodes>
      <leafValues>
        -5.0952082872390747e-01 5.6360706686973572e-02</leafValues></_>
    <_>
      <internalNodes>
        0 -1 184 -842897728 -41934750 -871355072 -552507392 1610927264
        809271472 1317032196 1360483139</internalNodes>
      <leafValues>
        -3.3460757136344910e-01 1.1061193794012070e-01</leafValues></_>
    <_>
      <internalNodes>
        0 -1 7529 -731925750 2034586998 -1675624328 -698650423 489964870
        1494380149 -1805360034 1143036793</internalNodes>
      <leafValues>
        -3.2400149106979370e-01 1.2712892889976501e-01</leafValues></_>
    <_>
      <internalNodes>
        0 -1 645 -652090232 2136471472 2080243316 -181328348 625139848
        1163736833 366029307 1363637407</internalNodes>
      <leafValues>
        -1.3147859275341034e-01 2.7158996462821960e-01</leafValues></_>
    <_>
      <internalNodes>
        0 -1 6948 1430230235 372718989 717029241 1206902747 1954338186
        794578943 402456447 -1644159873</internalNodes>
      <leafValues>
        -1.7395134270191193e-01 2.1701945364475250e-01</leafValues></_>
    <_>
      <internalNodes>
        0 -1 530 -506755444 453948208 3146388 1407479984 1896093704
        153108752 -1185865249 282292690</internalNodes>
      <leafValues>
        -2.2286829352378845e-01 1.6772998869419098e-01</leafValues></_>
    <_>
      <internalNodes>
        0 -1 8280 -1028985144 -2017457270 -1978433494 -317725942
        -1196840485 162185635 289476613 387385346</internalNodes>
      <leafValues>
        -2.0782871544361115e-01 1.8596380949020386e-01</leafValues></_>
    <_>
      <internalNodes>
        0 -1 2693 -21178856 -15340778 -855774377 -177770953 607581915
        -92995849 -927990642 -355757192</internalNodes>
      <leafValues>
        -1.5244558453559875e-01 2.4034947156906128e-01</leafValues></_>
    <_>
      <internalNodes>
        0 -1 7454 -229385718 1744713048 1149779998 1619122392 1073979012
        2097291312 -943566134 1963161419</internalNodes>
      <leafValues>
        -2.1012920141220093e-01 1.7721024155616760e-01</leafValues></_>
    <_>
      <internalNodes>
        0 -1 1842 -294924631 -1557776473 -16798104 -770925278 -436295762
        796321630 2021599173 -211036782</internalNodes>
      <leafValues>
        -1.7301887273788452e-01 1.9984801113605499e-01</leafValues></_>
    <_>
      <internalNodes>
        0 -1 3466 -1278882782 -73686743 -1775070239 -263589552
        -1466699610 -1892507617 -757346192 -661327308</internalNodes>
      <leafValues>
        -2.1685291826725006e-01 1.6241148114204407e-01</leafValues></_>
    <_>
      <internalNodes>
        0 -1 1551 -75579688 1543197922 -1044382594 -1793992721
        -117571398 -793421908 1857541630 2070880171</internalNodes>
      <leafValues>
        -1.4651083946228027e-01 2.7487784624099731e-01</leafValues></_>
    <_>
      <internalNodes>
        0 -1 3546 -1585498993 530113850 -255135660 1746929406 508269020
        1308639570 -558108017 540846287</internalNodes>
      <leafValues>
        -2.8075703978538513e-01 1.3134936988353729e-01</leafValues></_>
    <_>
      <internalNodes>
        0 -1 1445 -1704285142 943810308 -2121950178 -380000012
        1457836656 1578799132 537701320 1074611736</internalNodes>
      <leafValues>
        -2.5865155458450317e-01 1.4340701699256897e-01</leafValues></_>
    <_>
      <internalNodes>
        0 -1 25 -1025846619 -521951360 -1554721523 223724617 1510133428
        -1200977615 67345216 427287191</internalNodes>
      <leafValues>
        -1.9509145617485046e-01 1.7688953876495361e-01</leafValues></_>
    <_>
      <internalNodes>
        0 -1 3208 -501492221 -309672756 -1610575642 1892569308
        -283455740 1301610514 411757496 -185359524</internalNodes>
      <leafValues>
        -2.0232526957988739e-01 1.7935396730899811e-01</leafValues></_>
    <_>
      <internalNodes>
        0 -1 7380 242388106 1007152419 1786906746 963356435 457346764
        1532889635 1855348826 1617971030</internalNodes>
      <leafValues>
        -2.8156971931457520e-01 1.2073849886655807e-01</leafValues></_>
    <_>
      <internalNodes>
        0 -1 5114 231100681 -1545341688 -401587776 1618661470 2057386013
        453084560 -210980800 -256460388</internalNodes>
      <leafValues>
        -3.4479114413261414e-01 9.9255330860614777e-02</leafValues></_>
    <_>
      <internalNodes>
        0 -1 990 -109450646 -1724929999 -830605585 1174006659 1529951412
        1856513152 -1303061798 1464843915</internalNodes>
      <leafValues>
        -1.4568625390529633e-01 2.4498835206031799e-01</leafValues></_>
    <_>
      <internalNodes>
        0 -1 564 -946474496 1670332506 -771631996 -1143897206
        -2109023831 1897402368 1628106881 -1852073499</internalNodes>
      <leafValues>
        -1.9682013988494873e-01 1.8124251067638397e-01</leafValues></_>
    <_>
      <internalNodes>
        0 -1 6448 -151533985 -1821407540 -211060957 1433370420
        1559489756 184547231 -77177336 -1723177876</internalNodes>
      <leafValues>
        -1.3339595496654510e-01 2.5869047641754150e-01</leafValues></_>
    <_>
      <internalNodes>
        0 -1 6497 968876046 -1196576641 -195358537 341024822 437556996
        229789752 1753195279 -1672651284</internalNodes>
      <leafValues>
        -2.3561319708824158e-01 1.4834389090538025e-01</leafValues></_>
    <_>
      <internalNodes>
        0 -1 177 -40113491 422488400 -1809735644 -534794031 416489656
        1879643521 93286874 29704130</internalNodes>
      <leafValues>
        -1.7590934038162231e-01 1.9251635670661926e-01</leafValues></_>
    <_>
      <internalNodes>
        0 -1 4282 -275346812 1001791746 1375896708 536920242 2030770013
        -2013165525 1224153060 -1273992508</internalNodes>
      <leafValues>
        -3.3539107441902161e-01 1.0537000745534897e-01</leafValues></_>
    <_>
      <internalNodes>
        0 -1 3019 1509885067 2037642420 -25556176 1307164418 -1103558693
        292157344 203953306 992848539</internalNodes>
      <leafValues>
        -1.4630216360092163e-01 2.4814754724502563e-01</leafValues></_>
    <_>
      <internalNodes>
        0 -1 3872 -1479813026 1553254118 1779744920 352645718 2056678274
        -2037251943 484195288 1647362009</internalNodes>
      <leafValues>
        -2.5933399796485901e-01 1.3561050593852997e-01</leafValues></_>
    <_>
      <internalNodes>
        0 -1 4936 -26215349 1604157336 -424120544 296568600 1685028547
        507834309 -253708818 -773901153</internalNodes>
      <leafValues>
        -1.3008910417556763e-01 3.0595508217811584e-01</leafValues></_>
    <_>
      <internalNodes>
        0 -1 2087 -1026635392 -1651359688 1431495474 -4104428 1921206007
        1771913426 747430130 -2070652782</internalNodes>
      <leafValues>
        -2.0785881578922272e-01 1.7119999229907990e-01</leafValues></_>
    <_>
      <internalNodes>
        0 -1 1296 -408705760 1804784472 -804240064 -455323502 1654105034
        -1174003680 1714266548 -255467044</internalNodes>
      <leafValues>
        -2.0813649892807007e-01 1.6563108563423157e-01</leafValues></_>
    <_>
      <internalNodes>
        0 -1 6528 -27326902 1268187262 -1073734644 -2145232776
        1388759380 1887442432 1376446888 -1274882860</internalNodes>
      <leafValues>
        -2.9404368996620178e-01 1.1674583703279495e-01</leafValues></_>
    <_>
      <internalNodes>
        0 -1 8450 2054399627 -67109531 -29364228 -219971723 611970524
        -295772300 -34414678 -987513229</internalNodes>
      <leafValues>
        -1.2877696752548218e-01 2.8856796026229858e-01</leafValues></_>
    <_>
      <internalNodes>
        0 -1 571 -546196559 -111480899 -339980289 -317620321 -750007153
        -1422715420 1943137247 -550509077</internalNodes>
      <leafValues>
        -8.7273329496383667e-02 4.0187847614288330e-01</leafValues></_>
    <_>
      <internalNodes>
        0 -1 3083 -1067514872 1516964406 -2012947420 539000888
        -1285013500 688238846 -122807460 1612777498</internalNodes>
      <leafValues>
        -4.8745515942573547e-01 7.7259786427021027e-02</leafValues></_>
    <_>
      <internalNodes>
        0 -1 3626 -106240647 1610481080 -67217708 -14024705 -1887547413
        798259034 2012937422 -106324845</internalNodes>
      <leafValues>
        -1.1220029741525650e-01 3.5038945078849792e-01</leafValues></_>
    <_>
      <internalNodes>
        0 -1 928 1056927159 -570569059 -540095401 -706416897 1577023413
        1532788183 -150999873 -67174416</internalNodes>
      <leafValues>
        -9.4209529459476471e-02 3.7793898582458496e-01</leafValues></_>
    <_>
      <internalNodes>
        0 -1 1423 788063232 577826891 571687498 -1073555383 -90350072
        -296698936 1123205138 13595012</internalNodes>
      <leafValues>
        -4.5981884002685547e-01 8.6892552673816681e-02</leafValues></_>
    <_>
      <internalNodes>
        0 -1 4529 -190447567 559744963 -1064662910 1686516502 1898085228
        1343424072 -1305808928 -258812460</internalNodes>
      <leafValues>
        -3.1867802143096924e-01 1.1043033748865128e-01</leafValues></_>
    <_>
      <internalNodes>
        0 -1 8361 -360730885 2122268663 -1166279065 1970789850
        -1082148918 -42827908 1744615323 -550248482</internalNodes>
      <leafValues>
        -8.7181165814399719e-02 4.3444707989692688e-01</leafValues></_>
    <_>
      <internalNodes>
        0 -1 5397 -757241560 434692788 414544 604643720 -1557958292
        -1034288591 -599426249 -1334033048</internalNodes>
      <leafValues>
        -3.4839341044425964e-01 1.0365027189254761e-01</leafValues></_>
    <_>
      <internalNodes>
        0 -1 8181 -226230749 -34679701 -703546194 -749221759 -1157377236
        1228114442 -510728467 -244227341</internalNodes>
      <leafValues>
        -1.6647918522357941e-01 2.2540904581546783e-01</leafValues></_>
    <_>
      <internalNodes>
        0 -1 7001 -798268376 359461910 1946813777 1220844480 1913289349
        1636436864 1103157774 1940406584</internalNodes>
      <leafValues>
        -3.1966269016265869e-01 1.1309058219194412e-01</leafValues></_>
    <_>
      <internalNodes>
        0 -1 72 -810752558 -1281860092 1761027251 1836942897 -700980199
        380237216 1408716187 -1254664833</internalNodes>
      <leafValues>
        -1.5158715844154358e-01 2.4074944853782654e-01</leafValues></_>
    <_>
      <internalNodes>
        0 -1 8295 -873208680 -349213051 -1141019860 1307164423
        -822108738 -2055921859 2105435339 -1286630078</internalNodes>
      <leafValues>
        -1.2278021126985550e-01 2.9600411653518677e-01</leafValues></_>
    <_>
      <internalNodes>
        0 -1 331 -882399277 1607976084 -312709439 -539388479 509332922
        -568893582 1063911135 1366288007</internalNodes>
      <leafValues>
        -1.0297573357820511e-01 3.4750807285308838e-01</leafValues></_>
    <_>
      <internalNodes>
        0 -1 6256 2065408034 710580233 -872163184 1756467395 -2013194740
        2120876103 -819060111 1349799996</internalNodes>
      <leafValues>
        -4.4575354456901550e-01 8.3771184086799622e-02</leafValues></_>
    <_>
      <internalNodes>
        0 -1 744 1334891939 428823012 -1559173687 1576059232 270258933
        -1634062173 67797121 -1510072251</internalNodes>
      <leafValues>
        -1.8944530189037323e-01 1.9289167225360870e-01</leafValues></_>
    <_>
      <internalNodes>
        0 -1 1366 -203688703 -478095292 -465463162 1886646994 -116817784
        496435419 671780320 -1048616288</internalNodes>
      <leafValues>
        -1.9264417886734009e-01 1.9274604320526123e-01</leafValues></_>
    <_>
      <internalNodes>
        0 -1 809 -382600451 -148542345 -2021994635 -4908953 1320998585
        -88147225 -789577781 -471905457</internalNodes>
      <leafValues>
        -1.0427104681730270e-01 3.5132136940956116e-01</leafValues></_>
    <_>
      <internalNodes>
        0 -1 6392 -2040796369 -1547990565 -1005563572 -1029815857
        2047213622 34834624 -922590844 -465262908</internalNodes>
      <leafValues>
        -3.7586510181427002e-01 1.0011056065559387e-01</leafValues></_>
    <_>
      <internalNodes>
        0 -1 7660 -1851007335 -68237595 1677121499 -617629649 -269944903
        -1765283848 628419722 -1616161089</internalNodes>
      <leafValues>
        -9.0202473104000092e-02 4.0994802117347717e-01</leafValues></_>
    <_>
      <internalNodes>
        0 -1 63 -1745971235 -1885753762 1844703049 1976692303 2143268235
        -497745994 -735177313 565735083</internalNodes>
      <leafValues>
        -1.4969493448734283e-01 2.3953942954540253e-01</leafValues></_>
    <_>
      <internalNodes>
        0 -1 5912 572139528 224903627 -234852322 33574927 25410321
        -1370783726 414718384 -193561740</internalNodes>
      <leafValues>
        -3.8798096776008606e-01 9.6686154603958130e-02</leafValues></_>
    <_>
      <internalNodes>
        0 -1 5736 -106634029 1483104124 -361103507 2078879474 1853542077
        1198978886 -755849318 -148646101</internalNodes>
      <leafValues>
        -1.0997558385133743e-01 3.6024501919746399e-01</leafValues></_>
    <_>
      <internalNodes>
        0 -1 4699 262936394 246403384 -665791119 1882361996 1216872916
        -628972919 -1547431748 268439596</internalNodes>
      <leafValues>
        -3.9557021856307983e-01 9.5157131552696228e-02</leafValues></_>
    <_>
      <internalNodes>
        0 -1 1436 -1968562804 -1279940688 -83925408 1638198628 393207765
        -1923129881 1286977755 -1007730286</internalNodes>
      <leafValues>
        -1.7026473581790924e-01 2.1727237105369568e-01</leafValues></_>
    <_>
      <internalNodes>
        0 -1 3190 -667393368 -1599929914 -1073332120 -1965930098
        -1878302892 1841037322 1808457908 -1592352824</internalNodes>
      <leafValues>
        -2.9173171520233154e-01 1.2904788553714752e-01</leafValues></_>
    <_>
      <internalNodes>
        0 -1 496 1862596417 1170723738 -2058024832 1371066370 50440021
        -2036774269 462586852 -2076763614</internalNodes>
      <leafValues>
        -2.5585296750068665e-01 1.4530088007450104e-01</leafValues></_>
    <_>
      <internalNodes>
        0 -1 3328 1605953755 -1274500443 1676385505 -1868444152
        1567767842 -1637949602 1568464859 1006067592</internalNodes>
      <leafValues>
        -1.6886019706726074e-01 2.3136836290359497e-01</leafValues></_>
    <_>
      <internalNodes>
        0 -1 1978 -236198637 -478756983 1860697458 2070409762
        -1563049989 -1657045024 -1870834546 -778062341</internalNodes>
      <leafValues>
        -1.1170028150081635e-01 3.3517473936080933e-01</leafValues></_></weakClassifiers></stage8>
</opencv_storage>
